noipy/__init__.py
noipy/authinfo.py
noipy/dnsupdater.py
noipy/main.py
noipy/utils.py
noipy-2.0.0.dist-info/licenses/LICENSE
noipy-2.0.0.dist-info/METADATA
noipy-2.0.0.dist-info/WHEEL
noipy-2.0.0.dist-info/entry_points.txt
noipy-2.0.0.dist-info/top_level.txt
noipy-2.0.0.dist-info/zip-safe
noipy-2.0.0.dist-info/RECORD
